client_throttler/__init__.py
client_throttler/configs.py
client_throttler/constants.py
client_throttler/decorators.py
client_throttler/exceptions.py
client_throttler/metrics.py
client_throttler/redis.py
client_throttler/throttler.py
client_throttler-2.1.0.dist-info/licenses/LICENSE
client_throttler-2.1.0.dist-info/METADATA
client_throttler-2.1.0.dist-info/WHEEL
client_throttler-2.1.0.dist-info/top_level.txt
client_throttler-2.1.0.dist-info/RECORD
