Metadata-Version: 2.4
Name: client_throttler
Version: 2.1.0
Summary: A client throttle tool based on redis.
Home-page: https://github.com/OVINC-CN/ClientThrottler
Author: Raja
Author-email: contact@ovinc.cn
License: MIT
Classifier: Programming Language :: Python :: 3.6
Classifier: Programming Language :: Python :: 3.7
Classifier: Programming Language :: Python :: 3.8
Classifier: Programming Language :: Python :: 3.9
Classifier: Programming Language :: Python :: 3.10
Classifier: Operating System :: OS Independent
Classifier: License :: OSI Approved :: MIT License
Requires-Python: >=3.6, <4
License-File: LICENSE
Requires-Dist: redis>=3.2.0
Dynamic: author
Dynamic: author-email
Dynamic: classifier
Dynamic: description
Dynamic: description-content-type
Dynamic: home-page
Dynamic: license
Dynamic: license-file
Dynamic: requires-dist
Dynamic: requires-python
Dynamic: summary
